[
  {
    "id": "bu1",
    "cn": "Huron Skipper",
    "sn": "Atalopedes huron",
    "fam": "Hesperiidae",
    "famCommon": "skippers",
    "obs": 927,
    "wiki": "https://en.wikipedia.org/wiki/Atalopedes_huron",
    "st": "common",
    "desc": "Formerly Sachem - a ubiquitous later summer Skipper. This abundant Skipper is worth learning carefully as it has a lot of variation and you will see it more frequently then any other Skipper.",
    "fm": {
      "Wingspan": "Zabulon/Hobomok Skipper size",
      "Upperside": "Look for Large black patch on forewing.  Female with two pale spots on Forewing.",
      "Underside": "Female with pale crecent, Male paler with dark patch on Hindwing",
      "Flight Period": "Mid-Summer to Early Fall",
      "Host Plants": "Bermuda and Crab Grasses",
      "Habitat": "Backyards, fields and many other open areas"
    },
    "mo": [
      7,
      8,
      9,
      10
    ],
    "pk": [
      7,
      8,
      9
    ],
    "hp": "",
    "pkSrc": "pub"
  },
  {
    "id": "bu2",
    "cn": "Monarch",
    "sn": "Danaus plexippus",
    "fam": "Nymphalidae",
    "famCommon": "brushfoots",
    "obs": 785,
    "wiki": "http://en.wikipedia.org/wiki/Monarch_butterfly",
    "st": "common",
    "desc": "This is probably the most familiar butterfly.  Beautiful orange wings with black veins and white spots.",
    "fm": {
      "Wingspan": "2 inches (large)",
      "Upperside": "Orange with black veins and white spots",
      "Underside": "Orange with black veins",
      "Flight Period": "Early Summer to Late Fall",
      "Host Plants": "Milkweed",
      "Habitat": "Fields and open areas. Can be seen migrating in Fall."
    },
    "mo": [
      6,
      7,
      8,
      9,
      10
    ],
    "pk": [
      7,
      8,
      9
    ],
    "hp": "",
    "pkSrc": "pub"
  },
  {
    "id": "bu3",
    "cn": "Eastern Tiger Swallowtail",
    "sn": "Papilio glaucus",
    "fam": "Papilionidae",
    "famCommon": "swallowtails",
    "obs": 640,
    "wiki": "http://en.wikipedia.org/wiki/Papilio_glaucus",
    "st": "common",
    "desc": "Distinctive, yellow and black striped butterfly that sometimes shows a dark morph that could be confused with Black Swallowtail.",
    "fm": {
      "Wingspan": "2.5 inches (large)",
      "Upperside": "Yellow wings with black border and internal stripes.  Can show black morph.",
      "Underside": "Pale yellow with black border and bluish submarginal hindwing band",
      "Flight Period": "Spring and Summer",
      "Host Plants": "Wild Black Cherry and Tulip Tree",
      "Habitat": "Woodlands and forest edges"
    },
    "mo": [
      4,
      5,
      6,
      7,
      8,
      9
    ],
    "pk": [
      7,
      8
    ],
    "hp": "",
    "pkSrc": "pub"
  },
  {
    "id": "bu4",
    "cn": "Black Swallowtail",
    "sn": "Papilio polyxenes",
    "fam": "Papilionidae",
    "famCommon": "swallowtails",
    "obs": 580,
    "wiki": "http://en.wikipedia.org/wiki/Papilio_polyxenes",
    "st": "uncommon",
    "desc": "While Black is our most common black swallowtail, Eastern Tiger Swallow tail frequently shows a dark morph and Spicebrush Swallowtail, seen briefly can cause identification issues.  Black and Tiger have different shapes which may be helpful but a careful examination of wing pattern, especially underwing pattern, might be key to unlocking a dark Swallowtail's true identity.",
    "fm": {
      "Wingspan": "1.5 in, smaller than Eastern Tiger Swallowtail",
      "Upperside": "Forewing distinctive with yellow spotting on Male and Females.",
      "Underside": "lacks orange spots on forewing. Hindwing with orange and blue spots.",
      "Flight Period": "Spring through early Fall",
      "Host Plants": "Parsley, Carrot and Fennel",
      "Habitat": "Disturbed fields, gardens and meadows"
    },
    "mo": [
      5,
      6,
      7,
      8,
      9,
      10
    ],
    "pk": [
      6,
      7,
      8,
      9
    ],
    "hp": "",
    "pkSrc": "pub"
  },
  {
    "id": "bu5",
    "cn": "Small White",
    "sn": "Pieris rapae",
    "fam": "Pieridae",
    "famCommon": "sulphurs",
    "obs": 409,
    "wiki": "http://en.wikipedia.org/wiki/Pieris_rapae",
    "st": "common",
    "desc": "A ubiquitous butterfly found in many habitats. Underwings can be quite colorful but often seen in flight when white wings are obvious.",
    "fm": {
      "Wingspan": "< 1 inch (medium-small)",
      "Upperside": "White with three black spots",
      "Underside": "White, not heavily marked.  Can look quite yellowish.",
      "Flight Period": "Spring through Fall",
      "Host Plants": "Crucifers",
      "Habitat": "Open fields, gardens and disturbed areas"
    },
    "mo": [
      4,
      5,
      6,
      7,
      8,
      9,
      10
    ],
    "pk": [
      4,
      6,
      7,
      8,
      9
    ],
    "hp": "",
    "pkSrc": "pub"
  },
  {
    "id": "bu6",
    "cn": "Zabulon Skipper",
    "sn": "Lon zabulon",
    "fam": "Hesperiidae",
    "famCommon": "skippers",
    "obs": 355,
    "wiki": "https://en.wikipedia.org/wiki/Zabulon_skipper",
    "st": "common",
    "desc": "A small grass Skipper with dramatic sexual dimorphism. At times this species is abundant.  Worth spending time with it when available as getting to know its sexual and individual variation inside-out may help alert you to other species.  Similar to Hobomock Skipper but with distinctive underwing patterns.",
    "fm": {
      "Wingspan": "<1 inch",
      "Upperside": "Male hindwing with bright yellow-orange bordered with black.  Female with disinctive white spots on forewing.",
      "Underside": "Male yellow-orange circling dark patch on hindwing.  Female darker with pale edge to hindwing.",
      "Flight Period": "Spring to Mid Summer",
      "Host Plants": "Grasses",
      "Habitat": "Edge of woodlands and open areas"
    },
    "mo": [
      5,
      6,
      7,
      8
    ],
    "pk": [
      5,
      8
    ],
    "hp": "",
    "pkSrc": "pub"
  },
  {
    "id": "bu7",
    "cn": "Peck's Skipper",
    "sn": "Polites peckius",
    "fam": "Hesperiidae",
    "famCommon": "skippers",
    "obs": 306,
    "wiki": "http://en.wikipedia.org/wiki/Polites_peckius",
    "st": "common",
    "desc": "A very small skipper with distinctive underwing pattern.",
    "fm": {
      "Wingspan": "0.5 inches (small)",
      "Upperside": "Not especially distinctive, but look to hindwing with long pale central patch.",
      "Underside": "Variable but distinctive. Pale submarginal border with central cell much longer than others.",
      "Flight Period": "Late Summer",
      "Host Plants": "Grasses",
      "Habitat": "Open areas with nectar, various habitats."
    },
    "mo": [
      5,
      6,
      7,
      8,
      9
    ],
    "pk": [
      7,
      8,
      9
    ],
    "hp": "",
    "pkSrc": "pub"
  },
  {
    "id": "bu8",
    "cn": "Red-spotted Admiral",
    "sn": "Limenitis arthemis",
    "fam": "Nymphalidae",
    "famCommon": "brushfoots",
    "obs": 292,
    "wiki": "http://en.wikipedia.org/wiki/Limenitis_arthemis",
    "st": "uncommon",
    "desc": "A striking black and blue butterfly similar in appearance to Pipevine Swallowtail. Also know as Red-spotted Purple.",
    "fm": {
      "Wingspan": "<1 inch",
      "Upperside": "Black with iridescent blue. Orange spots on forewing.",
      "Underside": "White and black margined wtih orange spots submarginally on forewing and hindwing.",
      "Flight Period": "Spring and Summer",
      "Host Plants": "Cherry",
      "Habitat": "Woodlands and suburban areas. Varied."
    },
    "mo": [
      5,
      6,
      7,
      8,
      9
    ],
    "pk": [
      7,
      8,
      9
    ],
    "hp": "",
    "pkSrc": "pub"
  },
  {
    "id": "bu9",
    "cn": "Eastern Tailed-Blue",
    "sn": "Cupido comyntas",
    "fam": "Lycaenidae",
    "famCommon": "blues/hairstreaks",
    "obs": 260,
    "wiki": "http://en.wikipedia.org/wiki/Eastern_tailed-blue",
    "st": "common",
    "desc": "A small blue butterfly that flys low to the ground with distinctive tail-like extensions on the hindwings.",
    "fm": {
      "Wingspan": "0.5 inches (small)",
      "Upperside": "Blue with small tails on hindwing and orange spots.",
      "Underside": "blue-gray with orange spot on hindwing near tails.",
      "Flight Period": "Spring through Fall.",
      "Host Plants": "Pea family",
      "Habitat": "Open and disturbed areas."
    },
    "mo": [
      4,
      5,
      6,
      7,
      8,
      9,
      10
    ],
    "pk": [
      5,
      7,
      8,
      9
    ],
    "hp": "",
    "pkSrc": "pub"
  },
  {
    "id": "bu10",
    "cn": "Silver-spotted Skipper",
    "sn": "Epargyreus clarus",
    "fam": "Hesperiidae",
    "famCommon": "skippers",
    "obs": 237,
    "wiki": "http://en.wikipedia.org/wiki/Epargyreus_clarus",
    "st": "common",
    "desc": "A medium sized spreadwing skipper with distinctive silver band on the hindwing and large orange stripe on forewing.  Only Hoary Edge a much less common butterfly should pose any real identification issues.  Silver-spotteds are conspiculous and un-shy.",
    "fm": {
      "Wingspan": "1.25 inches (medium)",
      "Upperside": "Brownish or tawny. Forewing shape somewhat triangular",
      "Underside": "White or white-gold bandlike spot on hindwing. Visible in flight.",
      "Flight Period": "Late Summer and Early Fall",
      "Host Plants": "Black Locust and other legumes",
      "Habitat": "Various open habitats and woodland edges."
    },
    "mo": [
      5,
      6,
      7,
      8,
      9
    ],
    "pk": [
      6,
      7,
      8
    ],
    "hp": "",
    "pkSrc": "pub"
  },
  {
    "id": "bu11",
    "cn": "Red Admiral",
    "sn": "Vanessa atalanta",
    "fam": "Nymphalidae",
    "famCommon": "brushfoots",
    "obs": 234,
    "wiki": "http://en.wikipedia.org/wiki/Vanessa_atalanta",
    "st": "common",
    "desc": "A distinctive black butterfly with red bands and white spots.",
    "fm": {
      "Wingspan": ">1 inch",
      "Upperside": "Black with stunning red bands on forewing and hindwing",
      "Underside": "similar to Ladies butterflies",
      "Flight Period": "Spring through early Fall",
      "Host Plants": "Nettles",
      "Habitat": "Open areas with nectar sources"
    },
    "mo": [
      4,
      5,
      6,
      7,
      8,
      9
    ],
    "pk": [
      5,
      6,
      7,
      8
    ],
    "hp": "",
    "pkSrc": "pub"
  },
  {
    "id": "bu12",
    "cn": "Pearl Crescent",
    "sn": "Phyciodes tharos",
    "fam": "Nymphalidae",
    "famCommon": "brushfoots",
    "obs": 211,
    "wiki": "http://en.wikipedia.org/wiki/Pearl_crescent",
    "st": "common",
    "desc": "An abundant little butterfly with a spreadwing behavior that can be numerous in open areas.",
    "fm": {
      "Wingspan": "3/4 inch",
      "Upperside": "mosaic orange & black wings with strong blackish border",
      "Underside": "Not often seen, pale or warmly golden",
      "Flight Period": "Summer and Fall",
      "Host Plants": "Asters",
      "Habitat": "Open fields, whether meadows or backyards"
    },
    "mo": [
      4,
      5,
      6,
      7,
      8,
      9,
      10
    ],
    "pk": [
      5,
      7,
      8,
      9
    ],
    "hp": "",
    "pkSrc": "pub"
  },
  {
    "id": "bu13",
    "cn": "Common Buckeye",
    "sn": "Junonia coenia",
    "fam": "Nymphalidae",
    "famCommon": "brushfoots",
    "obs": 210,
    "wiki": "http://en.wikipedia.org/wiki/Junonia_coenia",
    "st": "common",
    "desc": "A prolific flyer, often seen on migration.  Easily identifiable in flight with it's pale forewing bars.",
    "fm": {
      "Wingspan": "~1 inch",
      "Upperside": "Pale bar on forewing and several 'eyes' around margin of FW and HW.",
      "Underside": "More cryptic, pale FW bar still visible",
      "Flight Period": "Summer and Fall",
      "Host Plants": "Gerardia and Toadflax",
      "Habitat": "Open, distrubed and Sandy areas."
    },
    "mo": [
      7,
      8,
      9,
      10,
      11
    ],
    "pk": [
      8,
      9,
      10
    ],
    "hp": "",
    "pkSrc": "pub"
  },
  {
    "id": "bu14",
    "cn": "Spicebush Swallowtail",
    "sn": "Papilio troilus",
    "fam": "Papilionidae",
    "famCommon": "swallowtails",
    "obs": 204,
    "wiki": "http://en.wikipedia.org/wiki/Papilio_troilus",
    "st": "uncommon",
    "desc": "Very similar to Black Swallowtail but lacks yellow markings.  Could also be confused with Red Spotted Admiral or Pipevine Swallowtail which is much less common in our area.",
    "fm": {
      "Wingspan": "~Black Swallowtail sized",
      "Upperside": "Black with bluish-white markings especially in hindwing",
      "Underside": "Two rows of orange dots on hindwing, no yellow.",
      "Flight Period": "Spring and Summer",
      "Host Plants": "Sassafras and Spicebush",
      "Habitat": "Woodland borders"
    },
    "mo": [
      5,
      6,
      7,
      8,
      9
    ],
    "pk": [
      7,
      8
    ],
    "hp": "",
    "pkSrc": "pub"
  },
  {
    "id": "bu15",
    "cn": "Variegated Fritillary",
    "sn": "Euptoieta claudia",
    "fam": "Nymphalidae",
    "famCommon": "brushfoots",
    "obs": 130,
    "wiki": "http://en.wikipedia.org/wiki/Euptoieta_claudia",
    "st": "uncommon",
    "desc": "A fairly unique butterfly. From above looks similar to other Fritillarys, with brownish-orange and pale wings with black cell borders and spotting.  From below it is quite different from our other Fritillarys.",
    "fm": {
      "Wingspan": ">American Lady butterfly",
      "Upperside": "Dramatic pattern of dull and pale orange bordered by black, some black spots.",
      "Underside": "Unlike other Fritillary butterflies, more cryptic with pale bar on HW",
      "Flight Period": "Summer and Fall",
      "Host Plants": "Violets",
      "Habitat": "Open fields with nectar flowers."
    },
    "mo": [
      7,
      8,
      9,
      10,
      11
    ],
    "pk": [
      7,
      8,
      9,
      10
    ],
    "hp": "",
    "pkSrc": "pub"
  },
  {
    "id": "bu16",
    "cn": "Eastern Comma",
    "sn": "Polygonia comma",
    "fam": "Nymphalidae",
    "famCommon": "brushfoots",
    "obs": 117,
    "wiki": "http://en.wikipedia.org/wiki/Polygonia_comma",
    "st": "uncommon",
    "desc": "Very similar to Question Mark and often and eespecially in flight may be indistinquishable.  Important to know the sex and to wait for it to land in order to examin spotting on forewing.",
    "fm": {
      "Wingspan": "Smaller than American Lady and Question Mark",
      "Upperside": "Orangish with fewer black spots in FW. HW can be dark or bright orange (brood specific)",
      "Underside": "Cryptic patern with pale comma.",
      "Flight Period": "Spring through early Fall",
      "Host Plants": "Elms and Nettles",
      "Habitat": "Wooded areas."
    },
    "mo": [
      3,
      4,
      5,
      6,
      7,
      8,
      9
    ],
    "pk": [
      3,
      4,
      5,
      6,
      7,
      8
    ],
    "hp": "",
    "pkSrc": "pub"
  },
  {
    "id": "bu17",
    "cn": "Red-banded Hairstreak",
    "sn": "Calycopis cecrops",
    "fam": "Lycaenidae",
    "famCommon": "blues/hairstreaks",
    "obs": 116,
    "wiki": "http://en.wikipedia.org/wiki/Red-banded_hairstreak",
    "st": "uncommon",
    "desc": "Probably the most common Hairstreak in the county and worth knowing well.  It has more orange on it's underwing than most Hairstreaks and moves North in late Summer when it becomes more common.",
    "fm": {
      "Wingspan": "Smaller than Gray Hairstreak.",
      "Upperside": "Bright blue.",
      "Underside": "A continuous orange-red band across HW and FW",
      "Flight Period": "Summer and Fall",
      "Host Plants": "Rotting leaves",
      "Habitat": "Wood edges, brushy fields and even backyards."
    },
    "mo": [
      5,
      6,
      7,
      8,
      9,
      10
    ],
    "pk": [
      8,
      9
    ],
    "hp": "",
    "pkSrc": "pub"
  },
  {
    "id": "bu18",
    "cn": "Orange Sulphur",
    "sn": "Colias eurytheme",
    "fam": "Pieridae",
    "famCommon": "sulphurs",
    "obs": 114,
    "wiki": "http://en.wikipedia.org/wiki/Colias_eurytheme",
    "st": "uncommon",
    "desc": "Very similar to Clouded Sulphur but with warmer orange coloring. Females may be indistinguishable.",
    "fm": {
      "Wingspan": "Similar to a Small White",
      "Upperside": "Only seen in flight, has yellow-orange coloration and black edging.",
      "Underside": "Males are more warmly colored, less of a blackish hue to leading edge.",
      "Flight Period": "Early Summer to Late Fall",
      "Host Plants": "Alfalfa and Fabaceae",
      "Habitat": "Open fields."
    },
    "mo": [
      6,
      7,
      8,
      9,
      10,
      11
    ],
    "pk": [
      7,
      8,
      9,
      10
    ],
    "hp": "",
    "pkSrc": "pub"
  },
  {
    "id": "bu19",
    "cn": "Summer Azure",
    "sn": "Celastrina neglecta",
    "fam": "Lycaenidae",
    "famCommon": "blues/hairstreaks",
    "obs": 95,
    "wiki": "http://en.wikipedia.org/wiki/Celastrina_neglecta",
    "st": "uncommon",
    "desc": "Basically the same as Spring Azure but flies later in the year.  It has no orange spotting and lacks tails.",
    "fm": {
      "Wingspan": "Bigger than an Eastern Tailed Blue.",
      "Upperside": "Blue with paler edging.  No tails, no red marks.",
      "Underside": "Pale with neat black markings",
      "Flight Period": "Summer and Fall",
      "Host Plants": "Varied diet",
      "Habitat": "Fields, backyards and open wooded areas."
    },
    "mo": [
      5,
      6,
      7,
      8,
      9
    ],
    "pk": [
      6,
      7,
      8
    ],
    "hp": "",
    "pkSrc": "pub"
  },
  {
    "id": "bu20",
    "cn": "American Lady",
    "sn": "Vanessa virginiensis",
    "fam": "Nymphalidae",
    "famCommon": "brushfoots",
    "obs": 92,
    "wiki": "http://en.wikipedia.org/wiki/American_painted_lady",
    "st": "uncommon",
    "desc": "A very close relative of the Painted Lady.  This pair, despite striking colors can pose identification issues if not seen well. American is the more deeply orange of the pair, especially in the leading edge of the FW.  It also has less black in the interior of the FW.",
    "fm": {
      "Wingspan": ">1 inch",
      "Upperside": "Orangish and black with several white spots on edge of forewing",
      "Underside": "Two 'eyes' on hindwing distinctive.",
      "Flight Period": "Spring through early Fall",
      "Host Plants": "Pearly Everlasting and other",
      "Habitat": "Open fields, roadsides and meadows."
    },
    "mo": [
      4,
      5,
      6,
      7,
      8,
      9,
      10
    ],
    "pk": [
      4,
      5,
      6,
      7,
      8
    ],
    "hp": "",
    "pkSrc": "pub"
  },
  {
    "id": "bu21",
    "cn": "Little Wood Satyr",
    "sn": "Megisto cymela",
    "fam": "Nymphalidae",
    "famCommon": "brushfoots",
    "obs": 90,
    "wiki": "http://en.wikipedia.org/wiki/Megisto_cymela",
    "st": "uncommon",
    "desc": "A ligth brown, understated and distinctive Butterfly with unique flight style. Can be quite common in appropriate habitat or the right time of year.",
    "fm": {
      "Wingspan": "3/4 of an inch",
      "Upperside": "Gray-brown with four eyes.",
      "Underside": "Gray-brown with two eyes on FW and HW.",
      "Flight Period": "Summer",
      "Host Plants": "Grasses",
      "Habitat": "Grassy areas next to woods and forest."
    },
    "mo": [
      5,
      6,
      7
    ],
    "pk": [
      6,
      7
    ],
    "hp": "",
    "pkSrc": "pub"
  },
  {
    "id": "bu22",
    "cn": "Gray Hairstreak",
    "sn": "Strymon melinus",
    "fam": "Lycaenidae",
    "famCommon": "blues/hairstreaks",
    "obs": 82,
    "wiki": "https://en.wikipedia.org/wiki/Gray_hairstreak",
    "st": "uncommon",
    "desc": "One of the larger and palest tailed Hairstreaks",
    "fm": {
      "Wingspan": "Larger than Red-banded Hairstreak",
      "Upperside": "Grayish-blue with one orange spot in HW.",
      "Underside": "Has narrow black & white bar across HW and FW. One to two large orange spots in HW.",
      "Flight Period": "Summer to Early Fall",
      "Host Plants": "Varied",
      "Habitat": "Disturbed areas, favors hilltops."
    },
    "mo": [
      6,
      7,
      8,
      9
    ],
    "pk": [
      7,
      8,
      9
    ],
    "hp": "",
    "pkSrc": "pub"
  },
  {
    "id": "bu23",
    "cn": "Least Skipper",
    "sn": "Ancyloxypha numitor",
    "fam": "Hesperiidae",
    "famCommon": "skippers",
    "obs": 76,
    "wiki": "http://en.wikipedia.org/wiki/Ancyloxypha_numitor",
    "st": "common",
    "desc": "Tiny orangish grass skipper",
    "fm": {
      "Wingspan": "< half an inch.",
      "Upperside": "Dark blackish wings",
      "Underside": "Brightly orange with rounded tips",
      "Flight Period": "Summer and Early Fall",
      "Host Plants": "Grasses",
      "Habitat": "Wet grassy areas and marshes, occasionally backyards."
    },
    "mo": [
      5,
      6,
      7,
      8,
      9
    ],
    "pk": [
      6,
      7,
      8,
      9
    ],
    "hp": "",
    "pkSrc": "pub"
  },
  {
    "id": "bu24",
    "cn": "Great Spangled Fritillary",
    "sn": "Argynnis cybele",
    "fam": "Nymphalidae",
    "famCommon": "brushfoots",
    "obs": 76,
    "wiki": "https://en.wikipedia.org/wiki/Great_spangled_fritillary",
    "st": "uncommon",
    "desc": "Large orange butterfly with conspicuous white spotting below.",
    "fm": {
      "Wingspan": "Nearly 2 inches",
      "Upperside": "Richly patterned Forewing contrasts with light patterning on HW.",
      "Underside": "Hindwing wtih pale white spots and wide creamy postmedian band",
      "Flight Period": "Summer",
      "Host Plants": "Violets",
      "Habitat": "Open fields and meadows."
    },
    "mo": [
      6,
      7,
      8,
      9
    ],
    "pk": [
      6,
      7
    ],
    "hp": "",
    "pkSrc": "pub"
  },
  {
    "id": "bu25",
    "cn": "Question Mark",
    "sn": "Polygonia interrogationis",
    "fam": "Nymphalidae",
    "famCommon": "brushfoots",
    "obs": 66,
    "wiki": "http://en.wikipedia.org/wiki/Polygonia_interrogationis",
    "st": "uncommon",
    "desc": "Very similar to Eastern Comma. Has two broods that are dimorphic.",
    "fm": {
      "Wingspan": "Larger than American Lady, bigger than E. Comma",
      "Upperside": "Orangish forwing has additional black dots.  Hindwing can be orange or black with pale edging",
      "Underside": "Cryptically mottled with a pale question mark.",
      "Flight Period": "Spr ing through early Fall",
      "Host Plants": "Nettles, Elm and Hackberry",
      "Habitat": "Open Woods and their borders."
    },
    "mo": [
      4,
      5,
      6,
      7,
      8,
      9,
      10
    ],
    "pk": [
      4,
      5,
      6,
      7,
      8,
      9
    ],
    "hp": "",
    "pkSrc": "pub"
  },
  {
    "id": "bu26",
    "cn": "Mourning Cloak",
    "sn": "Nymphalis antiopa",
    "fam": "Nymphalidae",
    "famCommon": "brushfoots",
    "obs": 65,
    "wiki": "http://en.wikipedia.org/wiki/Nymphalis_antiopa",
    "st": "uncommon",
    "desc": "A long living, distinctive looking butterfly.",
    "fm": {
      "Wingspan": "Nearly 2 inches",
      "Upperside": "Blackish with bold yellow trailing edge and blue submarginal spots.",
      "Underside": "Dark brownish/black-gray with paler border.",
      "Flight Period": "Spring through Fall",
      "Host Plants": "Many trees including Willows",
      "Habitat": "wide variety of habitat."
    },
    "mo": [
      3,
      4,
      5,
      6,
      7,
      9,
      10
    ],
    "pk": [
      3,
      4,
      5
    ],
    "hp": "",
    "pkSrc": "pub"
  },
  {
    "id": "bu27",
    "cn": "Painted Lady",
    "sn": "Vanessa cardui",
    "fam": "Nymphalidae",
    "famCommon": "brushfoots",
    "obs": 57,
    "wiki": "http://en.wikipedia.org/wiki/Vanessa_cardui",
    "st": "uncommon",
    "desc": "Very similar to American Lady, less orange and with more 'eyes' below on HW. Leading edge can have additional pale pink or almost white spot not seen in American lady.",
    "fm": {
      "Wingspan": ">1 inch",
      "Upperside": "Less orange compared to American Lady, pinkish with more black in forewing",
      "Underside": "at least four 'eye' spots in sub marginal section of hindwing distinctive.",
      "Flight Period": "Spring through early Fall",
      "Host Plants": "Many, including Thistles",
      "Habitat": "Varied open habitats."
    },
    "mo": [
      4,
      5,
      6,
      7,
      8,
      9,
      10
    ],
    "pk": [
      5,
      8,
      9,
      10
    ],
    "hp": "",
    "pkSrc": "pub"
  },
  {
    "id": "bu28",
    "cn": "Horace's Duskywing",
    "sn": "Erynnis horatius",
    "fam": "Hesperiidae",
    "famCommon": "skippers",
    "obs": 56,
    "wiki": "http://en.wikipedia.org/wiki/Erynnis_horatius",
    "st": "uncommon",
    "desc": "A large very dark spreadwing Skipper with several lookalikes.",
    "fm": {
      "Wingspan": "Similar to Northern Cloudywing.",
      "Upperside": "Very dark, male with small pale spot near FW Cell end. Female appears more mottled.",
      "Underside": "Very dark but lacks pale spots around top of Hindwing",
      "Flight Period": "Late Summer and Early Fall",
      "Host Plants": "Oaks",
      "Habitat": "Woods with Oak and adjacent open areas."
    },
    "mo": [
      7,
      8,
      9
    ],
    "pk": [
      7,
      8
    ],
    "hp": "",
    "pkSrc": "pub"
  },
  {
    "id": "bu29",
    "cn": "Wild Indigo Duskywing",
    "sn": "Erynnis baptisiae",
    "fam": "Hesperiidae",
    "famCommon": "skippers",
    "obs": 48,
    "wiki": "http://en.wikipedia.org/wiki/Erynnis_baptisiae",
    "st": "uncommon",
    "desc": "A small very dark spreadwing Skipper with mottled patterns.",
    "fm": {
      "Wingspan": "Smaller than Horace and Juvenal's.",
      "Upperside": "Has a patch of four white fingers on outer portion of forewing.",
      "Underside": "Very dark with a few white or light spots",
      "Flight Period": "Spring through early Fall",
      "Host Plants": "Wild Indigo, False Indigo, Vetch",
      "Habitat": "Varied open habitats."
    },
    "mo": [
      4,
      5,
      6,
      7,
      8,
      9
    ],
    "pk": [
      7,
      8
    ],
    "hp": "",
    "pkSrc": "pub"
  },
  {
    "id": "bu30",
    "cn": "Hackberry Emperor",
    "sn": "Asterocampa celtis",
    "fam": "Nymphalidae",
    "famCommon": "brushfoots",
    "obs": 42,
    "wiki": "http://en.wikipedia.org/wiki/Asterocampa_celtis",
    "st": "uncommon",
    "desc": "The more showy of our two Emperors.",
    "fm": {
      "Wingspan": "Size of American Lady",
      "Upperside": "White spotting in Forewing, hindwing lighter with black spots.",
      "Underside": "Cryptic but vibrant with many eyes along hindwing postmedian",
      "Flight Period": "Summer and Early Fall",
      "Host Plants": "Hackberry",
      "Habitat": "Typically near Hackberries."
    },
    "mo": [
      6,
      7,
      8,
      9
    ],
    "pk": [
      8
    ],
    "hp": "",
    "pkSrc": "pub"
  },
  {
    "id": "bu31",
    "cn": "Appalachian Brown",
    "sn": "Lethe appalachia",
    "fam": "Nymphalidae",
    "famCommon": "brushfoots",
    "obs": 38,
    "wiki": "http://en.wikipedia.org/wiki/Lethe_appalachia",
    "st": "uncommon",
    "desc": "Muted pale gray-brown appearance.",
    "fm": {
      "Wingspan": "Bigger than Little Wood Satyr.",
      "Upperside": "Pale gray-brown, typically lacking eye-spots in FW",
      "Underside": "Irrigular line of eyes in FW, straight lines on innner HW.",
      "Flight Period": "Summer and Early Fall",
      "Host Plants": "Sedges",
      "Habitat": "Wet woods and adjacent open areas."
    },
    "mo": [
      6,
      7,
      8,
      9
    ],
    "pk": [
      6,
      7,
      8
    ],
    "hp": "",
    "pkSrc": "pub"
  },
  {
    "id": "bu32",
    "cn": "Harvester",
    "sn": "Feniseca tarquinius",
    "fam": "Lycaenidae",
    "famCommon": "blues/hairstreaks",
    "obs": 31,
    "wiki": "http://en.wikipedia.org/wiki/Feniseca",
    "st": "uncommon",
    "desc": "A unique and unmistakable butterfly. Unlike many butterflies with carnivorous caterpillars - they eat Wooly Affids!",
    "fm": {
      "Wingspan": "Similar to Red-banded hairstreak",
      "Upperside": "Orange with blotchy black on the forewing",
      "Underside": "Patches of various shades of Orange with small pale white bubbles.",
      "Flight Period": "Spring through Fall",
      "Host Plants": "Wooly Aphids",
      "Habitat": "Woodlands, near water."
    },
    "mo": [
      5,
      6,
      7,
      8,
      9,
      10
    ],
    "pk": [
      5,
      6,
      7,
      8,
      9
    ],
    "hp": "",
    "pkSrc": "pub"
  },
  {
    "id": "bu33",
    "cn": "Appalachian Azure",
    "sn": "Celastrina neglectamajor",
    "fam": "Lycaenidae",
    "famCommon": "blues/hairstreaks",
    "obs": 30,
    "wiki": "http://en.wikipedia.org/wiki/Appalachian_azure",
    "st": "rare",
    "desc": "Basically identical to other Azures, but larger.  This one should be identified with caution.  Seeing it alongside a Summer Azure might be a good first step, or laying eggs on it's host plant. Of the ~30 records in iNaturalist, 29 are of catapillars and only one is of an adult butterfly.  ID we care!",
    "fm": {
      "Wingspan": "Larger than Summer Azure.",
      "Upperside": "Blue",
      "Underside": "Pale blue with neat black markings might be paler than Summer Azure",
      "Flight Period": "Early Summer",
      "Host Plants": "Black Cohosh",
      "Habitat": "Woodlands where Black Cohosh grows."
    },
    "mo": [
      5,
      6
    ],
    "pk": [
      6
    ],
    "hp": "",
    "pkSrc": "pub"
  },
  {
    "id": "bu34",
    "cn": "Cloudless Sulphur",
    "sn": "Phoebis sennae",
    "fam": "Pieridae",
    "famCommon":"sulphurs",
    "obs": 27,
    "wiki": "http://en.wikipedia.org/wiki/Phoebis_sennae",
    "st": "common",
    "desc": "A large, plain and colorful Sulphur.",
    "fm": {
      "Wingspan": "One third larger than Small White",
      "Upperside": "Only seen in flight.",
      "Underside": "Males lack most markings, females with some pink on FW and white spots on HW.",
      "Flight Period": "Fall",
      "Host Plants": "Cassias",
      "Habitat": "Open fields."
    },
    "mo": [
      8,
      9,
      10
    ],
    "pk": [
      8,
      9,
      10
    ],
    "hp": "",
    "pkSrc": "pub"
  },
  {
    "id": "bu35",
    "cn": "Clouded Sulphur",
    "sn": "Colias philodice",
    "fam": "Pieridae",
    "famCommon":"sulphurs",
    "obs": 27,
    "wiki": "http://en.wikipedia.org/wiki/Colias_philodice",
    "st": "common",
    "desc": "Very similar to Orange Sulphur but lacks orangish color.",
    "fm": {
      "Wingspan": "Similar to a Small White",
      "Upperside": "Only seen in flight, lacks orange typically.",
      "Underside": "Blackish border to leading edge of FW and HW.",
      "Flight Period": "Late Summer and Early Fall",
      "Host Plants": "White Clover",
      "Habitat": "Open fields."
    },
    "mo": [
      7,
      8,
      9,
      10
    ],
    "pk": [
      7,
      8
    ],
    "hp": "",
    "pkSrc": "pub"
  },
  {
    "id": "bu36",
    "cn": "Little Glassywing",
    "sn": "Vernia verna",
    "fam": "Hesperiidae",
    "famCommon":"skippers",
    "obs": 27,
    "wiki": "https://en.wikipedia.org/wiki/Vernia_verna",
    "st": "uncommon",
    "desc": "A dark Hespiria Skipper with distinctive FW spot.",
    "fm": {
      "Wingspan": "Similar to Tawny-edged Skipper",
      "Upperside": "Dark brown with a large square or rectangular pale spot. White on antenae",
      "Underside": "Dark brown with row of postmedial dots",
      "Flight Period": "Summer.",
      "Host Plants": "Purple-top Grass",
      "Habitat": "Brushy fields near woods."
    },
    "mo": [
      6,
      7
    ],
    "pk": [
      6
    ],
    "hp": "",
    "pkSrc": "pub"
  },
  {
    "id": "bu37",
    "cn": "Fiery Skipper",
    "sn": "Hylephila phyleus",
    "fam": "Hesperiidae",
    "famCommon":"skippers",
    "obs": 23,
    "wiki": "http://en.wikipedia.org/wiki/Fiery_skipper",
    "st": "uncommon",
    "desc": "A distinctive fall Grass Skipper.",
    "fm": {
      "Wingspan": "Smaller than Zabulon",
      "Upperside": "Orangish",
      "Underside": "Orangish with black dots on Hindwing.",
      "Flight Period": "Fall",
      "Host Plants": "Bermuda Grass",
      "Habitat": "Lawns and fields"
    },
    "mo": [
      8,
      9,
      10
    ],
    "pk": [
      9,
      10
    ],
    "hp": "",
    "pkSrc": "pub"
  },
  {
    "id": "bu38",
    "cn": "Swarthy Skipper",
    "sn": "Nastra lherminier",
    "fam": "Hesperiidae",
    "famCommon":"skippers",
    "obs": 23,
    "wiki": "http://en.wikipedia.org/wiki/Nastra_lherminier",
    "st": "uncommon",
    "desc": "A dull, small Grass Skipper. It really lacks a lof of the strong field marks our other Skippers display.",
    "fm": {
      "Wingspan": "Larger than Least Skipper",
      "Upperside": "Dull brownish",
      "Underside": "Yellowish-brown with prominent viens.",
      "Flight Period": "Summer",
      "Host Plants": "Little Bluestem",
      "Habitat": "Fields with bluestem."
    },
    "mo": [
      6,
      7,
      8
    ],
    "pk": [
      8
    ],
    "hp": "",
    "pkSrc": "pub"
  },
  {
    "id": "bu39",
    "cn": "Common Checkered-Skipper",
    "sn": "Burnsius communis",
    "fam": "Hesperiidae",
    "famCommon": "skippers",
    "obs": 23,
    "wiki": "https://en.wikipedia.org/wiki/Burnsius_communis",
    "st": "uncommon",
    "desc": "A delightful spreadwing Skipper.  This black and white beauty can't really be confused with anything else in our area.  The only surprise is the habitat you might find it in as it thrives in some of the most \"disturbed\" areas.",
    "fm": {
      "Wingspan": "Half an Inch",
      "Upperside": "Beautiful White with black checkerboard, bluish body",
      "Underside": "unlikely to see much of it.",
      "Flight Period": "Fall",
      "Host Plants": "Mallow Family (Malvaceae)",
      "Habitat": "Open and disturbed areas."
    },
    "mo": [
      5,
      8,
      9,
      10
    ],
    "pk": [
      8,
      9,
      10
    ],
    "hp": "",
    "pkSrc": "pub"
  },
  {
    "id": "bu40",
    "cn": "Dun Skipper",
    "sn": "Euphyes vestris",
    "fam": "Hesperiidae",
    "famCommon":"skippers",
    "obs": 18,
    "wiki": "http://en.wikipedia.org/wiki/Euphyes_vestris",
    "st": "uncommon",
    "desc": "Dark, mostly unmarked Hesperia Skipper",
    "fm": {
      "Wingspan": "Similar to Tawny-edged Skipper",
      "Upperside": "Males dark with black stigma.  Femailes Dark with at least two small spots.",
      "Underside": "Brownish and unmarked",
      "Flight Period": "Summer",
      "Host Plants": "Sedges",
      "Habitat": "Wet areas near woodland."
    },
    "mo": [
      6,
      7,
      8
    ],
    "pk": [
      6,
      8
    ],
    "hp": "",
    "pkSrc": "pub"
  },
  {
    "id": "bu41",
    "cn": "Eastern Giant Swallowtail",
    "sn": "Heraclides cresphontes",
    "fam": "Papilionidae",
    "famCommon":"swallowtails",
    "obs": 18,
    "wiki": "http://en.wikipedia.org/wiki/Papilio_cresphontes",
    "st": "uncommon",
    "desc": "A massive butterfly with distinct upperwing pattern. It's a slow flapper, almost gliding around but can move quickly enough.",
    "fm": {
      "Wingspan": "It's biiig",
      "Upperside": "Almost black with Yellow Bars forming X's in Forewing.",
      "Underside": "Creamy yellow with blue median band",
      "Flight Period": "Summer",
      "Host Plants": "Northern Prickly Ash, Common Rue",
      "Habitat": "Open woodland, adjacent fields and hilltops."
    },
    "mo": [
      5,
      7,
      8,
      9
    ],
    "pk": [
      5,
      7,
      8,
      9
    ],
    "hp": "",
    "pkSrc": "pub"
  },
  {
    "id": "bu42",
    "cn": "Juvenal's Duskywing",
    "sn": "Erynnis juvenalis",
    "fam": "Hesperiidae",
    "famCommon":"skippers",
    "obs": 17,
    "wiki": "http://en.wikipedia.org/wiki/Erynnis_juvenalis",
    "st": "uncommon",
    "desc": "Very similar to Horace's and should be identified with care.",
    "fm": {
      "Wingspan": "Similar to Northern Cloudywing.",
      "Upperside": "Males are almost entirely black with some mottling on outter edge. Females more black than Horace.",
      "Underside": "Pale edged with two pale spots on top of hindwing.",
      "Flight Period": "Spring",
      "Host Plants": "Oaks",
      "Habitat": "Woods with Oak and adjacent open areas."
    },
    "mo": [
      4,
      5
    ],
    "pk": [
      4,
      5
    ],
    "hp": "",
    "pkSrc": "pub"
  },
  {
    "id": "bu43",
    "cn": "Pipevine Swallowtail",
    "sn": "Battus philenor",
    "fam": "Papilionidae",
    "famCommon":"swallowtails",
    "obs": 16,
    "wiki": "https://en.wikipedia.org/wiki/Battus_philenor",
    "st": "uncommon",
    "desc": "A stunning dark blue Swallowtail. A few other Swallowtails or even a Red-spotted Admiral could be mistakenly ID as Pipevine but this species is unique.  Get a good look at one and it's easy to appreciate it's subtle shape and color differences.",
    "fm": {
      "Wingspan": "Similar to Black Swallowtail",
      "Upperside": "Dark with darkblue Hindwing.",
      "Underside": "Single band of orange spots on irridecent blue.",
      "Flight Period": "Summer and Fall",
      "Host Plants": "Pipevine",
      "Habitat": "wide variety of habitat."
    },
    "mo": [
      5,
      6,
      7,
      8,
      10
    ],
    "pk": [
      5,
      6,
      7,
      8,
      10
    ],
    "hp": "",
    "pkSrc": "pub"
  },
  {
    "id": "bu44",
    "cn": "American Snout",
    "sn": "Libytheana carinenta",
    "fam": "Nymphalidae",
    "famCommon":"brushfoots",
    "obs": 15,
    "wiki": "https://en.wikipedia.org/wiki/American_snout",
    "st": "uncommon",
    "desc": "A distinctive, tiny elephantine nosed butterfly. Snouts like to move around but aren't really fast, they are quick but have a certain floppyness to their flight.  Plus you can often spot the nose even in flight.",
    "fm": {
      "Wingspan": "Small, a bit bigger than a Pearl Crecent",
      "Upperside": "Brown and Orange with white marks at tip of pointed Forewing.",
      "Underside": "Hindwing cryptic, Forewing with splotch of orange",
      "Flight Period": "Spring and Summer",
      "Host Plants": "Hackberry",
      "Habitat": "Woods, brushy areas and adjacent open areas."
    },
    "mo": [
      4,
      6,
      7,
      8
    ],
    "pk": [
      4,
      6,
      7,
      8
    ],
    "hp": "",
    "pkSrc": "pub"
  },
  {
    "id": "bu45",
    "cn": "American Copper",
    "sn": "Lycaena hypophlaeas",
    "fam": "Lycaenidae",
    "famCommon":"blues/hairstreaks",
    "obs": 14,
    "wiki": "https://en.wikipedia.org/wiki/Lycaena_phlaeas",
    "st": "uncommon",
    "desc": "Like Hairstreaks but with vivid orange blocks on wing.",
    "fm": {
      "Wingspan": "Similar size to Red-banded Hairstreak",
      "Upperside": "Forewing with broad orange block spotted with black, HW graish with orange band.",
      "Underside": "Paler mirror of above wing appearance, black spotting more prominent.",
      "Flight Period": "Late Summer",
      "Host Plants": "Sheep Sorrel, Docks",
      "Habitat": "Open areas, particularly disturbed areas."
    },
    "mo": [
      6,
      8,
      9
    ],
    "pk": [
      6,
      8,
      9
    ],
    "hp": "",
    "pkSrc": "pub"
  },
  {
    "id": "bu46",
    "cn": "White M Hairstreak",
    "sn": "Parrhasius m-album",
    "fam": "Lycaenidae",
    "famCommon":"blues/hairstreaks",
    "obs": 13,
    "wiki": "http://en.wikipedia.org/wiki/Parrhasius_m-album",
    "st": "uncommon",
    "desc": "A beautiful Hairstreak to be enjoyed if seen.  Other Hairstreaks can alsoo show partial M-like markings on their hindwing.  Look also for orange limited to a single spot and a small white bar on the interior leading edge of the hindwing.",
    "fm": {
      "Wingspan": "Larger than Red-banded Hairstreak.",
      "Upperside": "Bright blue.",
      "Underside": "HW distinctive with single white bar internally near leading edge.  Distinctive white M near trailing edge and orange spot further from margin than other Hairstreaks.",
      "Flight Period": "Late Summer and Early Fall",
      "Host Plants": "Oaks",
      "Habitat": "Brushy fields, hilltops near Oak woodlands."
    },
    "mo": [
      4,
      7,
      8,
      9
    ],
    "pk": [
      4,
      7,
      8,
      9
    ],
    "hp": "",
    "pkSrc": "pub"
  },
  {
    "id": "bu47",
    "cn": "Banded Hairstreak",
    "sn": "Satyrium calanus",
    "fam": "Lycaenidae",
    "famCommon":"blues/hairstreaks",
    "obs": 12,
    "wiki": "http://en.wikipedia.org/wiki/Satyrium_calanus",
    "st": "uncommon",
    "desc": "A dull and featureless Hairstreak. Pale lines on underside are limited and fewer in number compared with rarer Striped Hairstreak.",
    "fm": {
      "Wingspan": "Similar size to Red-banded Hairstreak",
      "Upperside": "Grayish",
      "Underside": "Variable and muted.  Postmedian band has white markings only on outer edge.",
      "Flight Period": "Summer",
      "Host Plants": "Oaks, Hickories, Black Walnut",
      "Habitat": "Open fields with nectar flowers, near oak woodlands."
    },
    "mo": [
      6,
      7
    ],
    "pk": [
      6
    ],
    "hp": "",
    "pkSrc": "pub"
  },
  {
    "id": "bu48",
    "cn": "Sleepy Orange",
    "sn": "Eurema nicippe",
    "fam": "Pieridae",
    "famCommon":"sulphurs",
    "obs": 11,
    "wiki": "http://en.wikipedia.org/wiki/Eurema_nicippe",
    "st": "uncommon",
    "desc": "A late season visitor, similar to Orange Sulphur but with black antenae.",
    "fm": {
      "Wingspan": "Similar to a Small White",
      "Upperside": "Orange with black border, seen in flight.",
      "Underside": "Either yellow-ish orange or dull tanish-red with narrow dark wash diagonally.",
      "Flight Period": "Late Summer and Early Fall",
      "Host Plants": "Cassias",
      "Habitat": "Open fields."
    },
    "mo": [
      8,
      9
    ],
    "pk": [
      8,
      9
    ],
    "hp": "",
    "pkSrc": "pub"
  },
  {
    "id": "bu49",
    "cn": "Tawny-edged Skipper",
    "sn": "Polites themistocles",
    "fam": "Hesperiidae",
    "famCommon":"skippers",
    "obs": 10,
    "wiki": "http://en.wikipedia.org/wiki/Polites_themistocles",
    "st": "uncommon",
    "desc": "A dully colored Hespiria Skipper.",
    "fm": {
      "Wingspan": "Half an Inch",
      "Upperside": "Males dull on HW, FW with orange patch limited to leading edge, has black stigma.  Females with some pale spots and limited orange.",
      "Underside": "Dull HW contrasts with brighter FW that has some orange.  Males often showing faint or no spots.",
      "Flight Period": "Late Summer",
      "Host Plants": "Grasses",
      "Habitat": "Any open area near nectar sources."
    },
    "mo": [
      5,
      7,
      8
    ],
    "pk": [
      5,
      7,
      8
    ],
    "hp": "",
    "pkSrc": "pub"
  },
  {
    "id": "bu50",
    "cn": "Spring Azure",
    "sn": "Celastrina ladon",
    "fam": "Lycaenidae",
    "famCommon":"blues/hairstreaks",
    "obs": 10,
    "wiki": "http://en.wikipedia.org/wiki/Celastrina_ladon",
    "st": "common",
    "desc": "Virtualy identical to Summer Azure but flies in the spring.",
    "fm": {
      "Wingspan": "Smaller than ETB",
      "Upperside": "Blue",
      "Underside": "Pale blue with neat black markings, margin maybe muddier",
      "Flight Period": "April",
      "Host Plants": "Buds & Flowers of Dogwoods, Viburnums, New Jersey Tea",
      "Habitat": "wide variety of habitat."
    },
    "mo": [
      4
    ],
    "pk": [
      4
    ],
    "hp": "",
    "pkSrc": "pub"
  },
  {
    "id": "bu51",
    "cn": "Juniper Hairstreak",
    "sn": "Callophrys gryneus",
    "fam": "Lycaenidae",
    "famCommon":"blues/hairstreaks",
    "obs": 10,
    "wiki": "https://en.wikipedia.org/wiki/Callophrys_gryneus",
    "st": "rare",
    "desc": "A gorgeous emerald colored haristreak",
    "fm": {
      "Wingspan": "Smaller than Red-banded hairstreak",
      "Upperside": "Not often seen",
      "Underside": "It's a stunning green and brown with white.",
      "Flight Period": "Summer",
      "Host Plants": "Red Cedar",
      "Habitat": "Near Red Cedar groves."
    },
    "mo": [
      4,
      7
    ],
    "pk": [
      7
    ],
    "hp": "",
    "pkSrc": "pub"
  },
  {
    "id": "bu52",
    "cn": "Hobomok Skipper",
    "sn": "Lon hobomok",
    "fam": "Hesperiidae",
    "famCommon":"skippers",
    "obs": 9,
    "wiki": "https://en.wikipedia.org/wiki/Hobomok_skipper",
    "st": "rare",
    "desc": "Similar to much more common Zabulon Skipper.",
    "fm": {
      "Wingspan": "Same as Zabulon",
      "Upperside": "Male orange with bold black border, black cell end bars.  Female darker with pale cell spot.",
      "Underside": "Big brown splotch at base of wing with broad pale band centrally.  Lacks pale HW apex.",
      "Flight Period": "Summer.",
      "Host Plants": "Grasses",
      "Habitat": "Areas adjacent to decidous forest."
    },
    "mo": [
      5,
      6
    ],
    "pk": [
      5,
      6
    ],
    "hp": "",
    "pkSrc": "pub"
  },
  {
    "id": "bu53",
    "cn": "Baltimore Checkerspot",
    "sn": "Euphydryas phaeton",
    "fam": "Nymphalidae",
    "famCommon":"brushfoots",
    "obs": 8,
    "wiki": "http://en.wikipedia.org/wiki/Baltimore_checkerspot",
    "st": "rare",
    "desc": "A declining species(?) that is beautifuly colored.",
    "fm": {
      "Wingspan": "Size of American Lady",
      "Upperside": "Mostly black with white spots and orange border.",
      "Underside": "White and black, orange border and orange interior spots.",
      "Flight Period": "Spring and Summer",
      "Host Plants": "White Turtlehead",
      "Habitat": "Wet grassy areas and marshes with White Turtlehead, occasionally fields."
    },
    "mo": [
      5,
      6
    ],
    "pk": [
      5,
      6
    ],
    "hp": "",
    "pkSrc": "pub"
  },
  {
    "id": "bu54",
    "cn": "Tawny Emperor",
    "sn": "Asterocampa clyton",
    "fam": "Nymphalidae",
    "famCommon":"brushfoots",
    "obs": 7,
    "wiki": "https://en.wikipedia.org/wiki/Asterocampa_clyton",
    "st": "uncommon",
    "desc": "Superficially shares characters with several disparatly related butterflies.",
    "fm": {
      "Wingspan": "Size of American Lady",
      "Upperside": "Orange and black forewing, hindwing mostly. dark",
      "Underside": "Cryptic, lacking prominent eyes, some dark bands.",
      "Flight Period": "Late Summer",
      "Host Plants": "Hackberry",
      "Habitat": "Near Hackberries, but can be see in a variety of habitat."
    },
    "mo": [
      7,
      8
    ],
    "pk": [
      7,
      8
    ],
    "hp": "",
    "pkSrc": "pub"
  },
  {
    "id": "bu55",
    "cn": "Delaware Skipper",
    "sn": "Anatrytone logan",
    "fam": "Hesperiidae",
    "famCommon":"skippers",
    "obs": 6,
    "wiki": "http://en.wikipedia.org/wiki/Anatrytone_logan",
    "st": "uncommon",
    "desc": "A small orange Hesperia Skipper.",
    "fm": {
      "Wingspan": "Smaller than Zabulon",
      "Upperside": "Forewing orange with black cell end bar and black veining.",
      "Underside": "Unmarked yellow-orange.",
      "Flight Period": "Summer.",
      "Host Plants": "Grasses",
      "Habitat": "Brushy fields with sedges, wet fields."
    },
    "mo": [
      6,
      7
    ],
    "pk": [
      6,
      7
    ],
    "hp": "",
    "pkSrc": "pub"
  },
  {
    "id": "bu56",
    "cn": "Meadow Fritillary",
    "sn": "Boloria bellona",
    "fam": "Nymphalidae",
    "famCommon":"brushfoots",
    "obs": 6,
    "wiki": "http://en.wikipedia.org/wiki/Boloria_bellona",
    "st": "uncommon",
    "desc": "A small Frittilary.",
    "fm": {
      "Wingspan": "Larger than Pearl Crecent",
      "Upperside": "Orange and black, lacking black borders.",
      "Underside": "Smudy and indistict.",
      "Flight Period": "Summer",
      "Host Plants": "Violets",
      "Habitat": "Open fields and meadows."
    },
    "mo": [
      7
    ],
    "pk": [
      7
    ],
    "hp": "",
    "pkSrc": "pub"
  },
  {
    "id": "bu57",
    "cn": "Viceroy",
    "sn": "Limenitis archippus",
    "fam": "Nymphalidae",
    "famCommon":"brushfoots",
    "obs": 6,
    "wiki": "http://en.wikipedia.org/wiki/Viceroy_(butterfly)",
    "st": "uncommon",
    "desc": "Smaller and not closely related to similar looking Monarch.",
    "fm": {
      "Wingspan": "Smaller than Mourning Cloak.",
      "Upperside": "Very Orange, look for rounded band through Hindwing.",
      "Underside": "Similar to Monarch but note crecents in margin and round black line through HW.",
      "Flight Period": "Summer.",
      "Host Plants": "Willows",
      "Habitat": "Open areas, near water and Willows."
    },
    "mo": [
      7,
      8
    ],
    "pk": [
      7,
      8
    ],
    "hp": "",
    "pkSrc": "pub"
  },
  {
    "id": "bu58",
    "cn": "Falcate Orangetip",
    "sn": "Anthocharis midea",
    "fam": "Pieridae",
    "famCommon":"sulphurs",
    "obs": 6,
    "wiki": "https://en.wikipedia.org/wiki/Anthocharis_midea",
    "st": "rare",
    "desc": "A small early season show stopper.",
    "fm": {
      "Wingspan": "Smaller than Small White.",
      "Upperside": "White with orange Forewing tips. Female retains shape but not the orange.",
      "Underside": "Hindwing especially marbled, otherwise white.",
      "Flight Period": "Spring",
      "Host Plants": "Crucifers",
      "Habitat": "Open Woods with food source."
    },
    "mo": [
      4
    ],
    "pk": [
      4
    ],
    "hp": "",
    "pkSrc": "pub"
  },
  {
    "id": "bu59",
    "cn": "Broad-winged Skipper",
    "sn": "Poanes viator",
    "fam": "Hesperiidae",
    "famCommon":"skippers",
    "obs": 5,
    "wiki": "http://en.wikipedia.org/wiki/Poanes_viator",
    "st": "rare",
    "desc": "A large dull colored Hesperia Skipper.",
    "fm": {
      "Wingspan": "Larger than Zabulon",
      "Upperside": "Dark with several large orange spots",
      "Underside": "Dull orange brown, maybe with some paler spots.",
      "Flight Period": "Late Summer.",
      "Host Plants": "Common Reed, Wild Rice",
      "Habitat": "Irrupts(?) into our area, look for at nectar flowers."
    },
    "mo": [
      8
    ],
    "pk": [
      8
    ],
    "hp": "",
    "pkSrc": "pub"
  },
  {
    "id": "bu60",
    "cn": "Coral Hairstreak",
    "sn": "Satyrium titus",
    "fam": "Lycaenidae",
    "famCommon": "blues/hairstreaks",
    "obs": 4,
    "wiki": "https://en.wikipedia.org/wiki/Satyrium_titus",
    "st": "uncommon",
    "desc": "A tailless brownish-blue Hairstreak with striking HW.",
    "fm": {
      "Wingspan": "Similar to Red-banded hairstreak",
      "Upperside": "Brownish grayish blue",
      "Underside": "FW pale with some black dots, HW with striking row of coral spots near margin.",
      "Flight Period": "Summer",
      "Host Plants": "Prunus species",
      "Habitat": "Brushy fields, overgrown orchards."
    },
    "mo": [
      6
    ],
    "pk": [
      6
    ],
    "hp": "",
    "pkSrc": "pub"
  },
  {
    "id": "bu61",
    "cn": "Northern Broken-Dash",
    "sn": "Polites egeremet",
    "fam": "Hesperiidae",
    "famCommon": "skippers",
    "obs": 4,
    "wiki": "http://en.wikipedia.org/wiki/Wallengrenia_egeremet",
    "st": "uncommon",
    "desc": "A dull colored Hesperia Skipper best examined closely.",
    "fm": {
      "Wingspan": "Larger than Tawny-edged Skipper",
      "Upperside": "Both sexes have rectangular pale spot on FW. Male with two part stigma.",
      "Underside": "Light brownish sometimes with purple sheen. HW with spots sort of in shape of #3.",
      "Flight Period": "Summer.",
      "Host Plants": "Panicum grasses",
      "Habitat": "Open fields and meadows."
    },
    "mo": [
      6
    ],
    "pk": [
      6
    ],
    "hp": "",
    "pkSrc": "pub"
  },
  {
    "id": "bu62",
    "cn": "Common Sootywing",
    "sn": "Pholisora catullus",
    "fam": "Hesperiidae",
    "famCommon":"skippers",
    "obs": 3,
    "wiki": "http://en.wikipedia.org/wiki/Pholisora_catullus",
    "st": "rare",
    "desc": "A small dark spreadwinged Skipper.",
    "fm": {
      "Wingspan": "Half an Inch",
      "Upperside": "Dark with white spots on head and wings.",
      "Underside": "Not often seen.",
      "Flight Period": "Late Summer",
      "Host Plants": "Lambsquarters",
      "Habitat": "Heavily disturbed open areas."
    },
    "mo": [
      8
    ],
    "pk": [
      8
    ],
    "hp": "",
    "pkSrc": "pub"
  },
  {
    "id": "bu63",
    "cn": "Ocola Skipper",
    "sn": "Panoquina ocola",
    "fam": "Hesperiidae",
    "famCommon":"skippers",
    "obs": 3,
    "wiki": "http://en.wikipedia.org/wiki/Panoquina_ocola",
    "st": "rare",
    "desc": "A late summer visitor, distinctive.",
    "fm": {
      "Wingspan": "Longer than Zabulon",
      "Upperside": "Dark with translucent pale rounded comma shape in FW",
      "Underside": "Long narrow wing shape, occasionally with faint purplish sheen. Abdomen streaked.",
      "Flight Period": "Fall",
      "Host Plants": "Aquatic grasses",
      "Habitat": "Look for at nectar flowers."
    },
    "mo": [
      8,
      9,
      10
    ],
    "pk": [
      9
    ],
    "hp": "",
    "pkSrc": "pub"
  },
  {
    "id": "bu64",
    "cn": "Northern Cloudywing",
    "sn": "Cecropterus pylades",
    "fam": "Hesperiidae",
    "famCommon":"skippers",
    "obs": 3,
    "wiki": "http://en.wikipedia.org/wiki/Thorybes_pylades",
    "st": "rare",
    "desc": "A large dark skipper with limited markings.",
    "fm": {
      "Wingspan": "3/4 Inch",
      "Upperside": "Very dark with pale margin and limited white spots in Forewing",
      "Underside": "Very dark, somewhat splotchy",
      "Flight Period": "Summer",
      "Host Plants": "Legumes",
      "Habitat": "Open areas, both disturbed and meadow."
    },
    "mo": [
      6
    ],
    "pk": [
      6
    ],
    "hp": "",
    "pkSrc": "pub"
  },
  {
    "id": "bu65",
    "cn": "Crossline Skipper",
    "sn": "Limochores origenes",
    "fam": "Hesperiidae",
    "famCommon":"skippers",
    "obs": 3,
    "wiki": "http://en.wikipedia.org/wiki/Polites_origenes",
    "st": "uncommon",
    "desc": "A dull Hesperia Skipper similar to Tawny-edge",
    "fm": {
      "Wingspan": "Bigger than Tawny Edged Skipper",
      "Upperside": "Male with more orange than Tawny-edge, orange on both sides of stigma. Female with squarish pale spot near cell and less orange.",
      "Underside": "Similar to Tawny-edge but much less contrast between HW and FW leading edge.",
      "Flight Period": "Late Summer",
      "Host Plants": "Grasses",
      "Habitat": "Fields, open disturbed areas."
    },
    "mo": [
      7,
      8,
      9
    ],
    "pk": [
      8
    ],
    "hp": "",
    "pkSrc": "pub"
  },
  {
    "id": "bu66",
    "cn": "Common Wood-Nymph",
    "sn": "Cercyonis pegala",
    "fam": "Nymphalidae",
    "famCommon":"brushfoots",
    "obs": 2,
    "wiki": "http://en.wikipedia.org/wiki/Common_wood-nymph",
    "st": "uncommon",
    "desc": "Our largest Satyr, distinctive.",
    "fm": {
      "Wingspan": ">1 inch",
      "Upperside": "Only seen in flight. Brownish",
      "Underside": "Forewing has distinctive pale-yellowish patch with two eyes.",
      "Flight Period": "Summer.",
      "Host Plants": "Grasses",
      "Habitat": "Brushy fields, edge of woods."
    },
    "mo": [
      7
    ],
    "pk": [
      7
    ],
    "hp": "",
    "pkSrc": "pub"
  },
  {
    "id": "bu67",
    "cn": "Long-tailed Skipper",
    "sn": "Urbanus proteus",
    "fam": "Hesperiidae",
    "famCommon":"skippers",
    "obs": 2,
    "wiki": "http://en.wikipedia.org/wiki/Long-tailed_skipper",
    "st": "rare",
    "desc": "A Rockstar Skipper who visits from the South.  Distinctive coloration and shape.",
    "fm": {
      "Wingspan": "Smaller than Silver-spotted Skipper",
      "Upperside": "Long irridecent blueish tails on HW",
      "Underside": "Dark banding and pale edging",
      "Flight Period": "Late Summer and Early Fall",
      "Host Plants": "Grasses",
      "Habitat": "Nectaring on flowers"
    },
    "mo": [
      9
    ],
    "pk": [
      9
    ],
    "hp": "",
    "pkSrc": "pub"
  },
  {
    "id": "bu68",
    "cn": "Oak Hairstreak",
    "sn": "Satyrium favonius",
    "fam": "Lycaenidae",
    "famCommon":"blues/hairstreaks",
    "obs": 2,
    "wiki": "http://en.wikipedia.org/wiki/Satyrium_favonius",
    "st": "rare",
    "desc": "A rare hairstreak resembling White-M and Gray Hairstreaks.",
    "fm": {
      "Wingspan": "Smaller than Red-banded hairstreak",
      "Upperside": "Brownish gray blue",
      "Underside": "Lacks cell end bars. On HW, Orange spot with inner white border",
      "Flight Period": "Summer",
      "Host Plants": "Oaks",
      "Habitat": "Edge of woods."
    },
    "mo": [
      6
    ],
    "pk": [
      6
    ],
    "hp": "",
    "pkSrc": "pub"
  },
  {
    "id": "bu69",
    "cn": "Hoary Edge",
    "sn": "Cecropterus lyciades",
    "fam": "Hesperiidae",
    "famCommon":"skippers",
    "obs": 2,
    "wiki": "https://en.wikipedia.org/wiki/Cecropterus_lyciades",
    "st": "rare",
    "desc": "A dark and distinctive Skipper",
    "fm": {
      "Wingspan": "Smaller than Silver-spotted Skipper",
      "Upperside": "Dark, with translucent gold band in FW. Not as angular as Silver-spotted.",
      "Underside": "Pale margin to hindwing is bold.",
      "Flight Period": "Summer.",
      "Host Plants": "Tickseed and Legumes",
      "Habitat": "Open areas near woods, nectar flowers."
    },
    "mo": [
      6
    ],
    "pk": [
      6
    ],
    "hp": "",
    "pkSrc": "pub"
  },
  {
    "id": "bu70",
    "cn": "Northern Crescent",
    "sn": "Phyciodes cocyta",
    "fam": "Nymphalidae",
    "famCommon":"brushfoots",
    "obs": 1,
    "wiki": "http://en.wikipedia.org/wiki/Phyciodes_cocyta",
    "st": "uncommon",
    "desc": "Very Similar to Pearl Crecent",
    "fm": {
      "Wingspan": "Slightly larger than Pearl Crecent",
      "Upperside": "Males have more open orange in HW, females darker",
      "Underside": "Very similar to Pearl, possibly less patterned.",
      "Flight Period": "Summer.",
      "Host Plants": "Asters",
      "Habitat": "Open fields and meadows."
    },
    "mo": [
      6,
      7
    ],
    "pk": [
      7
    ],
    "hp": "",
    "pkSrc": "pub"
  },
  {
    "id": "bu71",
    "cn": "Milbert's Tortoiseshell",
    "sn": "Aglais milberti",
    "fam": "Nymphalidae",
    "famCommon":"brushfoots",
    "obs": 1,
    "wiki": "http://en.wikipedia.org/wiki/Aglais_milberti",
    "st": "rare",
    "desc": "A stunning, uniquely patternred butterfly.",
    "fm": {
      "Wingspan": "Smaller than American Lady",
      "Upperside": "Dark interior with firey yellow-orange band on outer edge of wing.",
      "Underside": "Similar to Mourning Cloak.",
      "Flight Period": "Spring through Fall.",
      "Host Plants": "Nettles",
      "Habitat": "Open fields, near woods."
    },
    "mo": [
      4,
      5,
      6,
      7,
      8,
      9,
      10
    ],
    "pk": [
      7,
      8
    ],
    "hp": "",
    "pkSrc": "pub"
  },
  {
    "id": "bu72",
    "cn": "Zebra Swallowtail",
    "sn": "Eurytides marcellus",
    "fam": "Papilionidae",
    "famCommon":"swallowtails",
    "obs": 1,
    "wiki": "http://en.wikipedia.org/wiki/Protographium_marcellus",
    "st": "rare",
    "desc": "An unique and unmistakable butterfly.",
    "fm": {
      "Wingspan": "Smaller than Black Swallowtail",
      "Upperside": "Triangular shaped white wings with black striping.",
      "Underside": "Below similar but red band visible.",
      "Flight Period": "Spring and Summer.",
      "Host Plants": "Pawpaw",
      "Habitat": "Open brushy fields along waterways."
    },
    "mo": [
      4,
      5,
      6,
      7,
      8
    ],
    "pk": [
      6
    ],
    "hp": "",
    "pkSrc": "pub"
  },
  {
    "id": "bu73",
    "cn": "Long Dash",
    "sn": "Limochores mystic",
    "fam": "Hesperiidae",
    "famCommon":"skippers",
    "obs": 1,
    "wiki": "https://en.wikipedia.org/wiki/Limochores_mystic",
    "st": "rare",
    "desc": "One iNaturalist observation in June.  Seen elsewhere in the state in Summer and Fall.",
    "fm": {
      "Wingspan": "Smaller than Zabulon",
      "Upperside": "Male Orange on either side of stigma. Female HW spots small in center (unlike Pecks).",
      "Underside": "Orange brown with yellow spotting and yellow cell spot.",
      "Flight Period": "Summer.",
      "Host Plants": "Grasses",
      "Habitat": "Dry fields, backyards."
    },
    "mo": [
      6
    ],
    "pk": [],
    "hp": "",
    "pkSrc": "pub"
  },
  {
    "id": "bu74",
    "cn": "Striped Hairstreak",
    "sn": "Satyrium liparops",
    "fam": "Lycaenidae",
    "famCommon":"blues/hairstreaks",
    "obs": 1,
    "wiki": "http://en.wikipedia.org/wiki/Satyrium_liparops",
    "st": "rare",
    "desc": "An unexpected Hairstreak with lots of namesake lines in underwing.",
    "fm": {
      "Wingspan":"Similar size to Red-banded Hairstreak",
      "Upperside": "Grayish-blue with one orange spot in HW.",
      "Underside": "Many stripes on FW and HW, orange post median spots.",
      "Flight Period":"Summer.",
      "Host Plants": "Cherries and Blueberries, varied range.",
      "Habitat": "Thickets, woodlands and their edge habitat."
    },
    "mo": [
      6
    ],
    "pk":[],
    "hp":"",
    "pkSrc": "pub"
  }
]